anaml_helper/__init__.py
anaml_helper/anaml_helper.py
anaml_helper-1.0.1.dist-info/METADATA
anaml_helper-1.0.1.dist-info/WHEEL
anaml_helper-1.0.1.dist-info/top_level.txt
anaml_helper-1.0.1.dist-info/RECORD
